LICENSE
MANIFEST.in
README.md
setup.py
fusionbox/__init__.py
fusionbox/fabric/__init__.py
fusionbox/fabric/config.py
fusionbox/fabric/git.py
fusionbox/fabric/update.py
fusionbox/fabric/utils.py
fusionbox/fabric/django/__init__.py
fusionbox/fabric/django/new.py
fusionbox/fabric/fborm/__init__.py
fusionbox/fabric/static/__init__.py
fusionbox_fabric_helpers.egg-info/PKG-INFO
fusionbox_fabric_helpers.egg-info/SOURCES.txt
fusionbox_fabric_helpers.egg-info/dependency_links.txt
fusionbox_fabric_helpers.egg-info/namespace_packages.txt
fusionbox_fabric_helpers.egg-info/requires.txt
fusionbox_fabric_helpers.egg-info/top_level.txt