Metadata-Version: 1.1
Name: fusionbox-fabric-helpers
Version: 0.6.1
Summary: Fabric Helpers
Home-page: https://github.com/fusionbox/fusionbox-fabric-helpers
Author: Fusionbox programmers
Author-email: programmers@fusionbox.com
License: BSD
Keywords: fabric helpers
Platform: UNKNOWN
Classifier: Environment :: Console
Classifier: Intended Audience :: Developers
Classifier: Intended Audience :: System Administrators
Classifier: Operating System :: MacOS :: MacOS X
Classifier: Operating System :: Unix
Classifier: Operating System :: POSIX
Classifier: Programming Language :: Python
Classifier: Programming Language :: Python :: 2.6
Classifier: Topic :: Software Development
Classifier: Topic :: Software Development :: Build Tools
Classifier: Topic :: Software Development :: Libraries
Classifier: Topic :: Software Development :: Libraries :: Python Modules
Classifier: Topic :: System :: Software Distribution
Classifier: Topic :: System :: Systems Administration
Requires: fabric
